wxauto/__init__.py
wxauto/color.py
wxauto/elements.py
wxauto/errors.py
wxauto/languages.py
wxauto/uiautomation.py
wxauto/utils.py
wxauto/wxauto.py
wxautold-3.9.11.17.5.dist-info/licenses/LICENSE
wxautold-3.9.11.17.5.dist-info/METADATA
wxautold-3.9.11.17.5.dist-info/WHEEL
wxautold-3.9.11.17.5.dist-info/top_level.txt
wxautold-3.9.11.17.5.dist-info/RECORD
