Metadata-Version: 2.4
Name: wxautold
Version: 3.9.11.17.5
Summary: A wxauto package
Author-email: wxautold <wxautold@qq.com>
Classifier: Programming Language :: Python :: 3
Classifier: License :: OSI Approved :: MIT License
Classifier: Operating System :: Microsoft :: Windows
Requires-Python: >=3.7
License-File: LICENSE
Requires-Dist: comtypes
Requires-Dist: pywin32
Requires-Dist: pyperclip
Requires-Dist: Pillow
Requires-Dist: psutil
Requires-Dist: typing-extensions
Dynamic: license-file
